LICENSE
MANIFEST.in
README.md
setup.py
django_ibantools.egg-info/PKG-INFO
django_ibantools.egg-info/SOURCES.txt
django_ibantools.egg-info/dependency_links.txt
django_ibantools.egg-info/top_level.txt
ibantools/__init__.py
ibantools/admin.py
ibantools/apps.py
ibantools/models.py
ibantools/operations.py
ibantools/tests.py
ibantools/utils.py
ibantools/locale/de/.DS_Store
ibantools/locale/de/LC_MESSAGES/django.mo
ibantools/locale/de/LC_MESSAGES/django.po
ibantools/management/__init__.py
ibantools/management/__init__.pyc
ibantools/management/commands/__init__.py
ibantools/management/commands/import_bundesbank_bankleitzahlen.py
ibantools/migrations/0001_initial.py
ibantools/migrations/0001_initial.pyc
ibantools/migrations/0002_auto_20180729_2216.py
ibantools/migrations/__init__.py
ibantools/migrations/__init__.pyc
ibantools/migrations/__pycache__/0001_initial.cpython-36.pyc
ibantools/migrations/__pycache__/__init__.cpython-36.pyc