Metadata-Version: 1.1
Name: django-ibantools
Version: 0.4.3
Summary: A simple IBAN/Bic Helper app
Home-page: https://github.com/nadobit/django-ibantools
Author: Bastian Probian
Author-email: contmp@me.com
License: BSD License
Platform: UNKNOWN
Classifier: Environment :: Web Environment
Classifier: Framework :: Django
Classifier: Framework :: Django :: 1.11
Classifier: Intended Audience :: Developers
Classifier: License :: OSI Approved :: BSD License
Classifier: Operating System :: OS Independent
Classifier: Programming Language :: Python
Classifier: Programming Language :: Python :: 3.0
Classifier: Topic :: Internet :: WWW/HTTP
